PyQt6ElaWidgetTools/ElaWidgetTools.abi3.so
PyQt6ElaWidgetTools/ElaWidgetTools.pyi
PyQt6ElaWidgetTools/__init__.py
pyqt6_elawidgettools-0.7.4.dist-info/METADATA
pyqt6_elawidgettools-0.7.4.dist-info/WHEEL
pyqt6_elawidgettools-0.7.4.dist-info/top_level.txt
pyqt6_elawidgettools-0.7.4.dist-info/RECORD
